{
  "user_device_rel": "1 person to n devices",
  "target_users": "Individual",
  "pid": "Klum2012",
  "focus": "Hardware; Software",
  "pid_done": "2",
  "scale": "Near, personal space",
  "input_modalities": "Stacking objects",
  "devices_included": "Tangibles",
  "use_cases_desc": "Any information seeking scenario that benefits from facetted browsing",
  "evaluation": "User study (quantitative, controlled lab experiment)",
  "contentlength": "8",
  "contribution_desc": "Stackable tangibles for faceted information seeking.",
  "pid_access": 1536780673,
  "device_models": "Sony Ericsson Xperia X10 mini",
  "output_modalities": "Screen output",
  "deployment": "Lab study",
  "interaction_techniques": "Cross-device task chaining; Data exploration; Visualisation",
  "connection_classification": "Local server",
  "toolkits": "Java; Android SDK; ",
  "tracking_characteristic": "Proximity; Identity; Inside-out tracking",
  "tracking_tech": "Arduino FIO micro-controller; Xbee wireless modem; Magnetic reed switch",
  "network_infrastructure": "WiFi; Xbee",
  "contribution": "Tracking technology; Interaction techniques; Display/Visualization technique"
}