{
  "target_users": "Expert users",
  "pid": "Schneegass2014",
  "focus": "Software",
  "device_mount": "Mounted to wall",
  "pid_done": "2",
  "scale": "Buildings; Room; Social space",
  "input_modalities": "3D gestures; Touch",
  "devices_included": "Public display",
  "evaluation": "User study (qualitative)",
  "contentlength": "5",
  "contribution_desc": "SenScreen, a toolkit that enables developers or large / public display applications to access low-level sensor information (e.g. tracking data from a Kinect or Leap Motion) through a high level Javascript API. \r\n\r\n\"To this server, arbitrary sensors via so-called adapters can be connected.\r\nAn API on the server enables client applications to obtain sensor data in a number of different formats.\"\r\n\r\nMultiple displays can use the same sensor information through accessing the server's API. ",
  "pid_access": 1533816891,
  "papertype": "Note",
  "tracking_characteristic": "Inside-out tracking; Location 3D; Tracking users only",
  "output_modalities": "Screen output",
  "deployment": "UX study",
  "interaction_techniques": "Data exploration; Remote control",
  "connection_classification": "Via remote server",
  "use_cases": "Entertainment; advertisement",
  "tracking_tech": "Kinect; Leap Motion; Asus Wavi Xtion; arbitrary - can be plugged in via adapters",
  "network_infrastructure": "Internet",
  "contribution": "Toolkit, middleware"
}